zeno/__init__.py
zeno/dichotomy.py
zeno/zeno.py
zeno-0.0.7.dist-info/LICENSE
zeno-0.0.7.dist-info/METADATA
zeno-0.0.7.dist-info/WHEEL
zeno-0.0.7.dist-info/entry_points.txt
zeno-0.0.7.dist-info/top_level.txt
zeno-0.0.7.dist-info/RECORD
