Metadata-Version: 2.1
Name: zeno
Version: 0.0.7
Summary: Zeno's Paradoxes Illustrated in Python
Home-page: UNKNOWN
Author: Ajay Khanna
Author-email: appliedstochastics@gmail.com
License: UNKNOWN
Platform: UNKNOWN
Classifier: Programming Language :: Python :: 3
Classifier: License :: OSI Approved :: GNU General Public License v3 (GPLv3)
Classifier: Operating System :: OS Independent
Requires-Python: >=3.6
License-File: LICENSE
